logging_metrics/__init__.py
logging_metrics/core.py
logging_metrics-0.2.3.dist-info/licenses/LICENSE
logging_metrics-0.2.3.dist-info/METADATA
logging_metrics-0.2.3.dist-info/WHEEL
logging_metrics-0.2.3.dist-info/top_level.txt
logging_metrics-0.2.3.dist-info/RECORD
