Metadata-Version: 2.4
Name: logging-metrics
Version: 0.2.3
Summary: Advanced logging utilities for robust, standardized logs in Python projects, APIs, data engineering, and more.
Author-email: Thaissa Ferreira <thaissa.teodoro@hotmail.com>
License-Expression: MIT
Project-URL: Repository, https://github.com/ThaissaTeodoro/logging-metrics
Project-URL: Changelog, https://https://github.com/ThaissaTeodoro/logging-metrics/blob/main/CHANGELOG.md
Keywords: logging,metrics,python,spark,instrumentation
Classifier: Development Status :: 4 - Beta
Classifier: Intended Audience :: Developers
Classifier: Programming Language :: Python :: 3
Classifier: Operating System :: OS Independent
Classifier: Topic :: Software Development :: Libraries
Requires-Python: >=3.9
License-File: LICENSE
Requires-Dist: pytz
Provides-Extra: dev
Requires-Dist: pytest>=7.0.0; extra == "dev"
Requires-Dist: pytest-cov>=4.0.0; extra == "dev"
Requires-Dist: pytest-xdist>=3.0.0; extra == "dev"
Requires-Dist: pytest-mock>=3.10.0; extra == "dev"
Requires-Dist: pyspark>=3.3.0; extra == "dev"
Requires-Dist: py4j>=0.10.9; extra == "dev"
Requires-Dist: coverage>=6.0.0; extra == "dev"
Requires-Dist: faker>=18.0.0; extra == "dev"
Requires-Dist: hypothesis>=6.0.0; extra == "dev"
Requires-Dist: black>=22.0.0; extra == "dev"
Requires-Dist: flake8>=5.0.0; extra == "dev"
Dynamic: license-file
